Workbook

Sheet Inputs
A1: Solace Goods — Business Model Inputs
A3: Starting Monthly Revenue | B3: 600000
A4: Starting Cash Balance | B4: 1500000
A5: Projection Months | B5: 12
A7: Fixed Costs (monthly)
A8: Rent | B8: 40000
A9: Salaries | B9: 180000
A10: Software/Tools | B10: 15000
A11: Other Overhead | B11: 25000
A12: Total Fixed Costs | B12: =SUM(B8:B11) -> 260000
A14: Variable Costs (% of Revenue)
A15: COGS % | B15: 0.35
A16: Marketing % | B16: 0.15

Sheet Scenarios
A1: Scenario Assumptions
A3: Scenario | B3: Monthly Growth Rate | C3: COGS % | D3: Marketing %
A4: Best Case | B4: 0.08 | C4: 0.32 | D4: 0.15
A5: Base Case | B5: 0.04 | C5: 0.35 | D5: 0.15
A6: Worst Case | B6: -0.02 | C6: 0.4 | D6: 0.18
A9: Active Scenario: | B9: Best Case

Sheet Calculations
A1: Model Calculations
A3: Active Growth Rate | B3: =INDEX(Scenarios!B4:B6,MATCH(Dashboard!D7,Scenarios!A4:A6,0)) -> 0.04
A4: Active COGS % | B4: =INDEX(Scenarios!C4:C6,MATCH(Dashboard!D7,Scenarios!A4:A6,0)) -> 0.35
A5: Active Marketing % | B5: =INDEX(Scenarios!D4:D6,MATCH(Dashboard!D7,Scenarios!A4:A6,0)) -> 0.15
A8: Month | B8: Revenue | C8: COGS | D8: Marketing | E8: Fixed Costs | F8: Net Cash Flow | G8: Cumulative Cash Balance | H8: H8 | J8: Metric | K8: Value
A9: 1 | B9: =Inputs!B3 -> 600000 | C9: =B9*B4 -> 210000 | D9: =B9*B5 -> 90000 | E9: =Inputs!B12 -> 260000 | F9: =B9-C9-D9-E9 -> 40000 | G9: =Inputs!B4+F9 -> 1540000 | H9: =0 -> 0 | J9: Month 1 Revenue | K9: =B9 -> 600000
A10: 2 | B10: =B9*(1+$B$3) -> 624000 | C10: =B10*$B$4 -> 218400 | D10: =B10*$B$5 -> 93600 | E10: =Inputs!$B$12 -> 260000 | F10: =B10-C10-D10-E10 -> 52000 | G10: =G9+F10 -> 1592000 | H10: =0 -> 0 | J10: Breakeven Revenue | K10: =B23 -> 520000
A11: 3 | B11: =B10*(1+$B$3) -> 648960 | C11: =B11*$B$4 -> 227136 | D11: =B11*$B$5 -> 97344 | E11: =Inputs!$B$12 -> 260000 | F11: =B11-C11-D11-E11 -> 64480 | G11: =G10+F11 -> 1656480 | H11: =0 -> 0
A12: 4 | B12: =B11*(1+$B$3) -> 674918.4 | C12: =B12*$B$4 -> 236221.44 | D12: =B12*$B$5 -> 101237.76 | E12: =Inputs!$B$12 -> 260000 | F12: =B12-C12-D12-E12 -> 77459.2 | G12: =G11+F12 -> 1733939.2 | H12: =0 -> 0
A13: 5 | B13: =B12*(1+$B$3) -> 701915.14 | C13: =B13*$B$4 -> 245670.3 | D13: =B13*$B$5 -> 105287.27 | E13: =Inputs!$B$12 -> 260000 | F13: =B13-C13-D13-E13 -> 90957.568 | G13: =G12+F13 -> 1824896.8 | H13: =0 -> 0
A14: 6 | B14: =B13*(1+$B$3) -> 729991.74 | C14: =B14*$B$4 -> 255497.11 | D14: =B14*$B$5 -> 109498.76 | E14: =Inputs!$B$12 -> 260000 | F14: =B14-C14-D14-E14 -> 104995.87 | G14: =G13+F14 -> 1929892.6 | H14: =0 -> 0
A15: 7 | B15: =B14*(1+$B$3) -> 759191.41 | C15: =B15*$B$4 -> 265716.99 | D15: =B15*$B$5 -> 113878.71 | E15: =Inputs!$B$12 -> 260000 | F15: =B15-C15-D15-E15 -> 119595.71 | G15: =G14+F15 -> 2049488.3 | H15: =0 -> 0
A16: 8 | B16: =B15*(1+$B$3) -> 789559.07 | C16: =B16*$B$4 -> 276345.67 | D16: =B16*$B$5 -> 118433.86 | E16: =Inputs!$B$12 -> 260000 | F16: =B16-C16-D16-E16 -> 134779.53 | G16: =G15+F16 -> 2184267.9 | H16: =0 -> 0
A17: 9 | B17: =B16*(1+$B$3) -> 821141.43 | C17: =B17*$B$4 -> 287399.5 | D17: =B17*$B$5 -> 123171.21 | E17: =Inputs!$B$12 -> 260000 | F17: =B17-C17-D17-E17 -> 150570.72 | G17: =G16+F17 -> 2334838.6 | H17: =0 -> 0
A18: 10 | B18: =B17*(1+$B$3) -> 853987.09 | C18: =B18*$B$4 -> 298895.48 | D18: =B18*$B$5 -> 128098.06 | E18: =Inputs!$B$12 -> 260000 | F18: =B18-C18-D18-E18 -> 166993.54 | G18: =G17+F18 -> 2501832.1 | H18: =0 -> 0
A19: 11 | B19: =B18*(1+$B$3) -> 888146.57 | C19: =B19*$B$4 -> 310851.3 | D19: =B19*$B$5 -> 133221.99 | E19: =Inputs!$B$12 -> 260000 | F19: =B19-C19-D19-E19 -> 184073.29 | G19: =G18+F19 -> 2685905.4 | H19: =0 -> 0
A20: 12 | B20: =B19*(1+$B$3) -> 923672.43 | C20: =B20*$B$4 -> 323285.35 | D20: =B20*$B$5 -> 138550.87 | E20: =Inputs!$B$12 -> 260000 | F20: =B20-C20-D20-E20 -> 201836.22 | G20: =G19+F20 -> 2887741.6 | H20: =0 -> 0
A22: Months to Cash-Out | B22: {=IFERROR(MATCH(TRUE,INDEX(G9:G20<0,0),0)&" months","12+ months")} -> 12+ months
A23: Breakeven Revenue (Monthly) | B23: =E9/(1-B4-B5) -> 520000
A25: Total Net Cash Flow | B25: =SUM(F9:F20) -> 1387741.6

Sheet Dashboard
C7: Scenario: | D7: Base Case
